core/MEMORY/instruction_memory.v
/*
----------------------------------------------------------------
                         RISC-V Core
                [ INSTRUCTION MEMORY ]
----------------------------------------------------------------
- Here we have created 32 byte memory and saved 8 instructions, each of length 4-bytes in the memory.
- As we can see, Instruction memory takes 2 arguments : 32 bit Program Counter and 1 bit reset
- the memory is initialized when reset is 1.
- When reset is not 1, instructions are assigned based on pc value.

*/

module instruction_memory(

    input [31:0] pc,
    input reset,
    output [31:0] instruction

);

    // Memory bank of 32 registers each of size 1 byte
    reg [7:0] Memory[31:0]; // 32 bytes memory

    // Here we will assign instruction code based on PC
    assign instruction = {Memory[pc+3], Memory[pc+2], Memory[pc+1], Memory[pc]};

    // When rest

    always @(reset)
      begin

        if (reset == 1)
        begin
        // Setting 32-bit instruction: add rd, rs1,rs2 => 0x00940333
        Memory[3] = 8'h00;
        Memory[2] = 8'h94;
        Memory[1] = 8'h03;
        Memory[0] = 8'h33;

        // Setting 32-bit instruction: sub rd, rs1,rs2 => 0x413903b3
        Memory[7] = 8'h41;
        Memory[6] = 8'h39;
        Memory[5] = 8'h03;
        Memory[4] = 8'hb3;

        // Setting 32-bit instruction: mul rd, rs1,rs2 => 0x035a02b3
        Memory[11] = 8'h03;
        Memory[10] = 8'h5a;
        Memory[9] = 8'h02;
        Memory[8] = 8'hb3;

        // Setting 32-bit instruction: xor rd, rs1,rs2 => 0x017b4e33
        Memory[15] = 8'h01;
        Memory[14] = 8'h7b;
        Memory[13] = 8'h4e;
        Memory[12] = 8'h33;

        // Setting 32-bit instruction: sll rd, rs1,rs2
        Memory[19] = 8'h01;
        Memory[18] = 8'h9c;
        Memory[17] = 8'h1e;
        Memory[16] = 8'hb3;

        // Setting 32-bit instruction: srl rd, rs1,rs2
        Memory[23] = 8'h01;
        Memory[22] = 8'hbd;
        Memory[21] = 8'h5f;
        Memory[20] = 8'h33;

        // Setting 32-bit instruction: and t6, a2, a3
        Memory[27] = 8'h00;
        Memory[26] = 8'hd6;
        Memory[25] = 8'h7f;
        Memory[24] = 8'hb3;

        // Setting 32-bit instruction: or a7, a4, a5
        Memory[31] = 8'h00;
        Memory[30] = 8'hf7;
        Memory[29] = 8'h68;
        Memory[28] = 8'hb3;
        end

      end


endmodule

core/FETCH/fetch.v
/*

----------------------------------------------------------------
                         RISC-V Core
                 [ INSTRUCTION FETCH UNIT ]
----------------------------------------------------------------
- Here Instruction Fetch unit take clock and reset as input and
  it outputs 32-bit instruction code on every positive edge of clock.
- It internally uses an instance of instruction memory which to
  output 32 instruction code.
- At each fetch operation, the program counter is incremented by 4      bytes.

*/

`include "./../MEMORY/instruction_memory.v"

module fetch(
    input clk,
    input reset,
    output [31:0] instruction
);

    // Initialize the program counter as zero
    reg [31:0] pc = 32'b0;

    // Instruction Memory Bank
    instruction_memory inst_mem(
        .pc(pc),
        .reset(reset),
        .instruction(instruction)
    );

    always @(posedge clk, posedge reset)
      begin

        if (reset == 1)
          pc <= 32'b0;    // reset the pc to zero
        else
          // pointing to next instruction
          pc <= pc+4;
      end
endmodule

core/FETCH/test_fetch.v
// Testbench for instruction fetch unit

`include "fetch.v"

module testbench();

    reg clk, reset;
    wire [31:0] instruction;

    fetch fetch_inst(
        .clk(clk),
        .reset(reset),
        .instruction(instruction)
    );

    // saving output wave
    initial
    begin
        $monitor($time, " clock=%b, reset=%b, instruction=%h", clk, reset, instruction);

        $dumpfile("output.vcd");
        $dumpvars(0, testbench);

    end

    // Initializing reset
    initial
      begin
        reset = 1'b1;
        #10  reset = 1'b0;
        #120 reset = 1'b1;
        #50  reset = 1'b0;
      end

    // Initializing clock
    initial
      begin
        clk = 1;
        forever #10 clk = ~clk;
      end

    initial
      #200 $finish();

endmodule

core/FETCH/output.vcd
$date
	Thu Feb 24 01:16:50 2022
$end
$version
	Icarus Verilog
$end
$timescale
	1s
$end
$scope module testbench $end
$var wire 32 ! instruction [31:0] $end
$var reg 1 " clk $end
$var reg 1 # reset $end
$scope module fetch_inst $end
$var wire 1 " clk $end
$var wire 1 # reset $end
$var wire 32 $ instruction [31:0] $end
$var reg 32 % pc [31:0] $end
$scope module inst_mem $end
$var wire 32 & pc [31:0] $end
$var wire 1 # reset $end
$var wire 32 ' instruction [31:0] $end
$upscope $end
$upscope $end
$upscope $end
$enddefinitions $end
#0
$dumpvars
b100101000000001100110011 '
b0 &
b0 %
b100101000000001100110011 $
1#
1"
b100101000000001100110011 !
$end
#10
0"
0#
#20
b1000001001110010000001110110011 !
b1000001001110010000001110110011 $
b1000001001110010000001110110011 '
b100 %
b100 &
1"
#30
0"
#40
b11010110100000001010110011 !
b11010110100000001010110011 $
b11010110100000001010110011 '
b1000 %
b1000 &
1"
#50
0"
#60
b1011110110100111000110011 !
b1011110110100111000110011 $
b1011110110100111000110011 '
b1100 %
b1100 &
1"
#70
0"
#80
b1100111000001111010110011 !
b1100111000001111010110011 $
b1100111000001111010110011 '
b10000 %
b10000 &
1"
#90
0"
#100
b1101111010101111100110011 !
b1101111010101111100110011 $
b1101111010101111100110011 '
b10100 %
b10100 &
1"
#110
0"
#120
b110101100111111110110011 !
b110101100111111110110011 $
b110101100111111110110011 '
b11000 %
b11000 &
1"
#130
b100101000000001100110011 !
b100101000000001100110011 $
b100101000000001100110011 '
b0 %
b0 &
0"
1#
#140
1"
#150
0"
#160
1"
#170
0"
#180
b1000001001110010000001110110011 !
b1000001001110010000001110110011 $
b1000001001110010000001110110011 '
b100 %
b100 &
1"
0#
#190
0"
#200
b11010110100000001010110011 !
b11010110100000001010110011 $
b11010110100000001010110011 '
b1000 %
b1000 &
1"
