core/constants.v
/*
		CONSTANTS USED IN THIS PROJECT	

*/

// Macros for different ALU operations

`define ADD		7'd0
`define SUB		7'd1
`define AND		7'd2
`define OR		7'd3
`define XOR		7'd4
`define MUL		7'd5
`define DIV		7'd6
`define DIVU	7'd7
`define REM		7'd10
`define REMU	7'd11
`define SLL		7'd8
`define SLTU    7'd9
`define SRL		7'd14
`define SRA		7'd15
`define LUI		7'd12
`define NONE	7'd13


// Macros for Instruction Types

`define REG    3'b000   // R-Type Instructions
`define IMM    3'b001   // Immediate Instruction
`define LUI    3'b010   // U-Type Instruction
`define STORE  3'b011   // Store Instructions
`define LOAD   3'b100   // Load Instructions
`define BRANCH 3'b101   // Branch Instructions
`define JMP    3'b110   // Jump Instructions
`define PCR    3'b111   // P-Type Instructions

core/ALU/alu.v
/*
----------------------------------------------------------------
                         RISC-V Core
                [ ARITHMATIC LOGIC UNIT (ALU) ]
----------------------------------------------------------------

- This ALU takes 2 inputs ip1 and ip2, each of size 32 bits.
- Here the 4 bit operation represents one of the 16 operations
  that can be done by this core.
- zero flag gets activated whenever the result of alu operation is 0.

*/

`include "./../constants.v"

module alu (

    input [31:0] ip1,
    input [31:0] ip2,
    input [6:0] operation,
    output reg [31:0] result,
    output reg zero_flag
);

    always @ (*)
      begin
        case (operation)

          `ADD  : result = ip1 + ip2;
          `SUB  : result = ip1 - ip2;
          `AND  : result = ip1 & ip2;
          `OR   : result = ip1 | ip2;
          `XOR  : result = ip1 ^ ip2;
          `MUL  : result = ip1*ip2;
          `DIV  : result = $signed(ip1) / $signed(ip2);
          `DIVU : result = ip1 / ip2;
          `REM  : result = $signed(ip1) % $signed(ip2);  // remainder
          `REMU : result = ip1 % ip2;           // remainder unsigned
          `SLL  : result = ip1 << ip2;          // Shift Left Logical
          `SLTU : result = ip1 < ip2 ? 1 : 0;   // Set Less Than Unsigned
          `SRL  : result = ip1 >> ip2;          // Shift Right Logical
          `SRA  : result = $signed(ip1) >> ip2; // Shift Right Arithmatic
          `LUI  : result = ip1 << 12;           // Load Upper Immediate
          `NONE : result = 0;                   // No Operation
        endcase

        if (result == 0)
          zero_flag = 1'b1;
        else
          zero_flag = 1'b0;

      end

endmodule

core/REGISTERS/register_file.v
/*
----------------------------------------------------------------
                         RISC-V Core
                      [ REGISTER FILE ]
--------------------------------------------------------------
- RISC-V base ISA consists of total 32 registers, each 32 bits wide.
- 31 of them are general-purpose registers r1-r31, which hold integer values.
- The register r0 is hardwired to the constant 0.
- We can use 5 bits to specify each register in register file for read and write operation.
- The register bank has 2 read ports and 1 write port.

*/

module reg_file(

    input clk,
    input reset,        // to reset the register file
    input [4:0] rs1,    // read_reg1 offset
    input [4:0] rs2,    // read_reg2 offset
    output [31:0] rd1,  // read_reg1 data
    output [31:0] rd2,  // read_reg2 data

    input write,
    input [4:0] rw,       // offset for write register
    input [31:0] rwd // register write data
    //input stall
);

    // 32 bit registers
    reg [31:0] r [31:0];

    // reset all register values
    always @ (posedge reset)
      begin
        r[0] =  32'b0;
        r[1] =  32'b0;
        r[2] =  32'b0;
        r[3] =  32'b0;
        r[4] =  32'b0;
        r[5] =  32'b0;
        r[6] =  32'b0;
        r[7] =  32'b0;
        r[8] =  32'b0;
        r[9] =  32'b0;
        r[10] = 32'b0;
        r[11] = 32'b0;
        r[12] = 32'b0;
        r[13] = 32'b0;
        r[14] = 32'b0;
        r[15] = 32'b0;
        r[16] = 32'b0;
        r[17] = 32'b0;
        r[18] = 32'b0;
        r[19] = 32'b0;
        r[20] = 32'b0;
        r[21] = 32'b0;
        r[22] = 32'b0;
        r[23] = 32'b0;
        r[24] = 32'b0;
        r[25] = 32'b0;
        r[26] = 32'b0;
        r[27] = 32'b0;
        r[28] = 32'b0;
        r[29] = 32'b0;
        r[30] <= 32'b0;
        r[31] = 32'b0;
      end

    // register write (except r0)
    always @ (posedge clk)
      begin
        if (write & rw!=0)
          r[rw] = rwd;
      end


    // register read  (except r0)
    assign rd1 = rs1==0 ? 32'b0 : r[rs1];
    assign rd2 = rs2==0 ? 32'b0 : r[rs2];

endmodule

core/DATAPATH/datapath.v
/*
----------------------------------------------------------------
                         RISC-V Core
                   [ PROCESSOR DATAPATH ]
----------------------------------------------------------------

This part of the processor contains the hardware connections
necessary to perform operations required by the processor.

*/

`include "./../ALU/alu.v"
`include "./../REGISTERS/register_file.v"

module datapath(
    input [4:0]rs1, // Source register 1 offset
    input [4:0]rs2, // Source register 2 offset
    input [4:0]rw,  // write register offset
    input [6:0]operation,
    input write,
    input clk,
    input reset,
    output zero_flag
);

    // interconnections wires between 'REGISTER FILE' and 'ALU'
    wire [31:0]rd1;  // source register 2 data
    wire [31:0]rd2;  // source register 2 data
    wire [31:0]rwd;  // Write register data

    // Creating register file instance
    reg_file register_inst(
        .clk(clk),
        .reset(reset),
        .rs1(rs1),
        .rs2(rs2),
        .rd1(rd1),
        .rd2(rd2),
        .rw(rw),
        .rwd(rwd),
        .write(write)
    );

    // Creating ALU instance
    alu alu_inst(
        .ip1(rd1),
        .ip2(rd2),
        .operation(operation),
        .result(rwd),
        .zero_flag(zero_flag)
    );

endmodule

core/DECODE/decode.v
/*
----------------------------------------------------------------
                         RISC-V Core
                   [ INSTRUCTION DECODER ]
----------------------------------------------------------------

- In this implementation of instruction decoder which takes an 32-bit
  instruction as input.
- It decodes 32 bit instruction into opcode, source registers and destination register

      -------------------------------------------------
      | opcode |   rd   | func3 |  rs1  |  rs2  | func7 |
      -------------------------------------------------
      0       6|7     11|12   14|15   19|20   24|25   31|

 - Here func3 indicated type of instruction (R-Type, Load/Store. Immediate, etc.)
 - Func7 is  used in immediate instructions.

*/

module decode(
    input [31:0] instruction,
    output reg [4:0] rs1,
    output reg [4:0] rs2,
    output reg [6:0] operation,
    output reg write,
    output reg [4:0] rw
);

    reg type; // temp
    always @(instruction)
      begin
        operation = instruction[6:0]; // opcode
        rs1 = instruction[24:20]; // source register 1
        rs2 = instruction[19:15]; // source register 2
        rw = instruction[11:7];   // destination register
        type = instruction[14:12]; // Type of Instruction

        write = (type == 3'b000) ? 1'b1 : 1'b0; // R-Type Instruction
      end

endmodule

core/MEMORY/instruction_memory.v
/*
----------------------------------------------------------------
                         RISC-V Core
                [ INSTRUCTION MEMORY ]
----------------------------------------------------------------
- Here we have created 32 byte memory and saved 8 instructions, each of length 4-bytes in the memory.
- As we can see, Instruction memory takes 2 arguments : 32 bit Program Counter and 1 bit reset
- the memory is initialized when reset is 1.
- When reset is not 1, instructions are assigned based on pc value.

*/

module instruction_memory(

    input [31:0] pc,
    input reset,
    output [31:0] instruction

);

    // Memory bank of 32 registers each of size 1 byte
    reg [7:0] Memory[31:0]; // 32 bytes memory

    // Here we will assign instruction code based on PC
    assign instruction = {Memory[pc+3], Memory[pc+2], Memory[pc+1], Memory[pc]};

    // When rest

    always @(reset)
      begin

        if (reset == 1)
        begin
        // Setting 32-bit instruction: add rd, rs1,rs2 => 0x00940333
        Memory[3] = 8'h00;
        Memory[2] = 8'h94;
        Memory[1] = 8'h03;
        Memory[0] = 8'h00;

        // Setting 32-bit instruction: sub rd, rs1,rs2 => 0x413903b3
        Memory[7] = 8'h41;
        Memory[6] = 8'h39;
        Memory[5] = 8'h03;
        Memory[4] = 8'h01;

        // Setting 32-bit instruction: mul rd, rs1,rs2 => 0x035a02b3
        Memory[11] = 8'h03;
        Memory[10] = 8'h5a;
        Memory[9] = 8'h02;
        Memory[8] = 8'h05;

        // Setting 32-bit instruction: xor rd, rs1,rs2 => 0x017b4e33
        Memory[15] = 8'h01;
        Memory[14] = 8'h7b;
        Memory[13] = 8'h4e;
        Memory[12] = 8'h04;

        // Setting 32-bit instruction: sll rd, rs1,rs2
        Memory[19] = 8'h01;
        Memory[18] = 8'h9c;
        Memory[17] = 8'h1e;
        Memory[16] = 8'h08;

        // Setting 32-bit instruction: srl rd, rs1,rs2
        Memory[23] = 8'h01;
        Memory[22] = 8'hbd;
        Memory[21] = 8'h5f;
        Memory[20] = 8'h0e;

        // Setting 32-bit instruction: and t6, a2, a3
        Memory[27] = 8'h00;
        Memory[26] = 8'hd6;
        Memory[25] = 8'h7f;
        Memory[24] = 8'h02;

        // Setting 32-bit instruction: or a7, a4, a5
        Memory[31] = 8'h00;
        Memory[30] = 8'hf7;
        Memory[29] = 8'h68;
        Memory[28] = 8'h03;
        end

      end


endmodule

core/FETCH/fetch.v
/*

----------------------------------------------------------------
                         RISC-V Core
                 [ INSTRUCTION FETCH UNIT ]
----------------------------------------------------------------
- Here Instruction Fetch unit take clock and reset as input and
  it outputs 32-bit instruction code on every positive edge of clock.
- It internally uses an instance of instruction memory which to
  output 32 instruction code.
- At each fetch operation, the program counter is incremented by 4      bytes.

*/

`include "./../MEMORY/instruction_memory.v"

module fetch(
    input clk,
    input reset,
    output [31:0] instruction
);

    // Initialize the program counter as zero
    reg [31:0] pc = 32'b0;

    // Instruction Memory Bank
    instruction_memory inst_mem(
        .pc(pc),
        .reset(reset),
        .instruction(instruction)
    );

    always @(posedge clk, posedge reset)
      begin

        if (reset == 1)
          pc <= 32'b0;    // reset the pc to zero
        else
          // pointing to next instruction
          pc <= pc+4;
      end
endmodule

core/PROCESSOR_CORE/core.v
/*

----------------------------------------------------------------
                         RISC-V Core
                      [ PROCESSOR CORE ]
----------------------------------------------------------------

-  Here we have Implemented complete processor by integrating
  different modules like Fetch, Decode, Datapath.

- In datapath module, I have combined 3 stages (execute, memory &
  write back.
*/

`include "./../FETCH/fetch.v"
`include "./../DATAPATH/datapath.v"
`include "./../DECODE/decode.v"


module core(
    input clk,
    input reset,
    output zero_flag
);

  wire [31:0] instruction;
  wire [6:0] operation;
  wire write;
  wire [4:0] rs1;
  wire [4:0] rs2;
  wire [4:0] rw;

  // Instruction Fetch Stage

  fetch instruction_fetch(
      .clk(clk),
      .reset(reset),
      .instruction(instruction)
  );


  // INstruction Decode Stage
  decode instruction_decode(
      .instruction(instruction),
      .rs1(rs1),
      .rs2(rs2),
      .operation(operation),
      .write(write),
      .rw(rw)
  );

  // Execute, Memory and Write Back Stage
  datapath datapath_module(
      .rs1(rs1),
      .rs2(rs1),
      .rw(rw),
      .operation(operation),
      .write(write),
      .clk(clk),
      .reset(reset),
      .zero_flag(zero_flag)
  );

endmodule

core/PROCESSOR_CORE/test_core.v
// testbench for processor core
`include "core.v"
module testbench();

    reg clk;
    reg reset;
    wire zero_flag;

    core test_core(
        .clk(clk),
        .reset(reset),
        .zero_flag(zero_flag)
    );

    // saving the output waveform
    initial
      begin
        $dumpfile("output.vcd");
        $dumpvars(0, testbench);
      end

    // initializing the clock signal
    initial
      begin
        clk = 0;
        forever #20 clk = ~clk;
      end

    // initializing reset signal
    initial
        begin
        reset  = 1;
        #10 reset = 0;
      end

    // simulation fnish time
    initial
      #400 $finish;

endmodule

core/PROCESSOR_CORE/output.vcd
$date
	Sat Feb 26 22:22:53 2022
$end
$version
	Icarus Verilog
$end
$timescale
	1s
$end
$scope module testbench $end
$var wire 1 ! zero_flag $end
$var reg 1 " clk $end
$var reg 1 # reset $end
$scope module test_core $end
$var wire 1 " clk $end
$var wire 1 # reset $end
$var wire 1 ! zero_flag $end
$var wire 1 $ write $end
$var wire 5 % rw [4:0] $end
$var wire 5 & rs2 [4:0] $end
$var wire 5 ' rs1 [4:0] $end
$var wire 7 ( operation [6:0] $end
$var wire 32 ) instruction [31:0] $end
$scope module datapath_module $end
$var wire 1 " clk $end
$var wire 1 # reset $end
$var wire 1 ! zero_flag $end
$var wire 1 $ write $end
$var wire 32 * rwd [31:0] $end
$var wire 5 + rw [4:0] $end
$var wire 5 , rs2 [4:0] $end
$var wire 5 - rs1 [4:0] $end
$var wire 32 . rd2 [31:0] $end
$var wire 32 / rd1 [31:0] $end
$var wire 7 0 operation [6:0] $end
$scope module alu_inst $end
$var wire 7 1 operation [6:0] $end
$var wire 32 2 ip2 [31:0] $end
$var wire 32 3 ip1 [31:0] $end
$var reg 32 4 result [31:0] $end
$var reg 1 ! zero_flag $end
$upscope $end
$scope module register_inst $end
$var wire 1 " clk $end
$var wire 1 # reset $end
$var wire 32 5 rwd [31:0] $end
$var wire 1 $ write $end
$var wire 5 6 rw [4:0] $end
$var wire 5 7 rs2 [4:0] $end
$var wire 5 8 rs1 [4:0] $end
$var wire 32 9 rd2 [31:0] $end
$var wire 32 : rd1 [31:0] $end
$upscope $end
$upscope $end
$scope module instruction_decode $end
$var wire 32 ; instruction [31:0] $end
$var reg 7 < operation [6:0] $end
$var reg 5 = rs1 [4:0] $end
$var reg 5 > rs2 [4:0] $end
$var reg 5 ? rw [4:0] $end
$var reg 1 @ type $end
$var reg 1 $ write $end
$upscope $end
$scope module instruction_fetch $end
$var wire 1 " clk $end
$var wire 1 # reset $end
$var wire 32 A instruction [31:0] $end
$var reg 32 B pc [31:0] $end
$scope module inst_mem $end
$var wire 32 C pc [31:0] $end
$var wire 1 # reset $end
$var wire 32 D instruction [31:0] $end
$upscope $end
$upscope $end
$upscope $end
$upscope $end
$enddefinitions $end
#0
$dumpvars
b100101000000001100110011 D
b0 C
b0 B
b100101000000001100110011 A
0@
b110 ?
b1000 >
b1001 =
b110011 <
b100101000000001100110011 ;
b0 :
b0 9
b1001 8
b1001 7
b110 6
bx 5
bx 4
b0 3
b0 2
b110011 1
b110011 0
b0 /
b0 .
b1001 -
b1001 ,
b110 +
bx *
b100101000000001100110011 )
b110011 (
b1001 '
b1000 &
b110 %
1$
1#
0"
0!
$end
#10
0#
#20
b111 %
b111 +
b111 6
b111 ?
b10010 &
b10010 >
b10011 '
b10011 ,
b10011 -
b10011 7
b10011 8
b10011 =
b1000001001110010000001110110011 )
b1000001001110010000001110110011 ;
b1000001001110010000001110110011 A
b1000001001110010000001110110011 D
b100 B
b100 C
1"
#40
0"
#60
b101 %
b101 +
b101 6
b101 ?
b10100 &
b10100 >
b10101 '
b10101 ,
b10101 -
b10101 7
b10101 8
b10101 =
b11010110100000001010110011 )
b11010110100000001010110011 ;
b11010110100000001010110011 A
b11010110100000001010110011 D
b1000 B
b1000 C
1"
#80
0"
#100
b11100 %
b11100 +
b11100 6
b11100 ?
b10110 &
b10110 >
b10111 '
b10111 ,
b10111 -
b10111 7
b10111 8
b10111 =
b1011110110100111000110011 )
b1011110110100111000110011 ;
b1011110110100111000110011 A
b1011110110100111000110011 D
b1100 B
b1100 C
1"
#120
0"
#140
0$
1@
b11101 %
b11101 +
b11101 6
b11101 ?
b11000 &
b11000 >
b11001 '
b11001 ,
b11001 -
b11001 7
b11001 8
b11001 =
b1100111000001111010110011 )
b1100111000001111010110011 ;
b1100111000001111010110011 A
b1100111000001111010110011 D
b10000 B
b10000 C
1"
#160
0"
#180
b11110 %
b11110 +
b11110 6
b11110 ?
b11010 &
b11010 >
b11011 '
b11011 ,
b11011 -
b11011 7
b11011 8
b11011 =
b1101111010101111100110011 )
b1101111010101111100110011 ;
b1101111010101111100110011 A
b1101111010101111100110011 D
b10100 B
b10100 C
1"
#200
0"
#220
b11111 %
b11111 +
b11111 6
b11111 ?
b1100 &
b1100 >
b1101 '
b1101 ,
b1101 -
b1101 7
b1101 8
b1101 =
b110101100111111110110011 )
b110101100111111110110011 ;
b110101100111111110110011 A
b110101100111111110110011 D
b11000 B
b11000 C
1"
#240
0"
#260
1$
0@
b10001 %
b10001 +
b10001 6
b10001 ?
b1110 &
b1110 >
b1111 '
b1111 ,
b1111 -
b1111 7
b1111 8
b1111 =
b111101110110100010110011 )
b111101110110100010110011 ;
b111101110110100010110011 A
b111101110110100010110011 D
b11100 B
b11100 C
1"
#280
0"
#300
bx .
bx 2
bx 9
bx /
bx 3
bx :
x$
x@
bx %
bx +
bx 6
bx ?
bx &
bx >
bx '
bx ,
bx -
bx 7
bx 8
bx =
bx (
bx 0
bx 1
bx <
bx )
bx ;
bx A
bx D
b100000 B
b100000 C
1"
#320
0"
#340
b100100 B
b100100 C
1"
#360
0"
#380
b101000 B
b101000 C
1"
