core/constants.v
/*
		CONSTANTS USED IN THIS PROJECT	

*/

// Macros for different ALU operations

`define ADD		7'd0
`define SUB		7'd1
`define AND		7'd2
`define OR		7'd3
`define XOR		7'd4
`define MUL		7'd5
`define DIV		7'd6
`define DIVU	7'd7
`define REM		7'd10
`define REMU	7'd11
`define SLL		7'd8
`define SLTU    7'd9
`define SRL		7'd14
`define SRA		7'd15
`define LUI		7'd12
`define NONE	7'd13


// Macros for Instruction Types

`define REG    3'b000   // R-Type Instructions
`define IMM    3'b001   // Immediate Instruction
`define LUI    3'b010   // U-Type Instruction
`define STORE  3'b011   // Store Instructions
`define LOAD   3'b100   // Load Instructions
`define BRANCH 3'b101   // Branch Instructions
`define JMP    3'b110   // Jump Instructions
`define PCR    3'b111   // P-Type Instructions

core/ALU/alu.v
/*
----------------------------------------------------------------
                         RISC-V Core
                [ ARITHMATIC LOGIC UNIT (ALU) ]
----------------------------------------------------------------

- This ALU takes 2 inputs ip1 and ip2, each of size 32 bits.
- Here the 4 bit operation represents one of the 16 operations
  that can be done by this core.
- zero flag gets activated whenever the result of alu operation is 0.

*/

`include "./../constants.v"

module alu (

    input [31:0] ip1,
    input [31:0] ip2,
    input [6:0] operation,
    output reg [31:0] result,
    output reg zero_flag
);

    always @ (*)
      begin
        case (operation)

          `ADD  : result = ip1 + ip2;
          `SUB  : result = ip1 - ip2;
          `AND  : result = ip1 & ip2;
          `OR   : result = ip1 | ip2;
          `XOR  : result = ip1 ^ ip2;
          `MUL  : result = ip1*ip2;
          `DIV  : result = $signed(ip1) / $signed(ip2);
          `DIVU : result = ip1 / ip2;
          `REM  : result = $signed(ip1) % $signed(ip2);  // remainder
          `REMU : result = ip1 % ip2;           // remainder unsigned
          `SLL  : result = ip1 << ip2;          // Shift Left Logical
          `SLTU : result = ip1 < ip2 ? 1 : 0;   // Set Less Than Unsigned
          `SRL  : result = ip1 >> ip2;          // Shift Right Logical
          `SRA  : result = $signed(ip1) >> ip2; // Shift Right Arithmatic
          `LUI  : result = ip1 << 12;           // Load Upper Immediate
          `NONE : result = 0;                   // No Operation
        endcase

        if (result == 0)
          zero_flag = 1'b1;
        else
          zero_flag = 1'b0;

      end

endmodule

core/REGISTERS/register_file.v
/*
----------------------------------------------------------------
                         RISC-V Core
                      [ REGISTER FILE ]
--------------------------------------------------------------
- RISC-V base ISA consists of total 32 registers, each 32 bits wide.
- 31 of them are general-purpose registers r1-r31, which hold integer values.
- The register r0 is hardwired to the constant 0.
- We can use 5 bits to specify each register in register file for read and write operation.
- The register bank has 2 read ports and 1 write port.

*/

module reg_file(

    input clk,
    input reset,        // to reset the register file
    input [4:0] rs1,    // read_reg1 offset
    input [4:0] rs2,    // read_reg2 offset
    output [31:0] rd1,  // read_reg1 data
    output [31:0] rd2,  // read_reg2 data

    input write,
    input [4:0] rw,       // offset for write register
    input [31:0] rwd // register write data
    //input stall
);

    // 32 bit registers
    reg [31:0] r [31:0];

    // reset all register values
    always @ (posedge reset)
      begin
        r[0] =  32'b0;
        r[1] =  32'b0;
        r[2] =  32'b0;
        r[3] =  32'b0;
        r[4] =  32'b0;
        r[5] =  32'b0;
        r[6] =  32'b0;
        r[7] =  32'b0;
        r[8] =  32'b0;
        r[9] =  32'b0;
        r[10] = 32'b0;
        r[11] = 32'b0;
        r[12] = 32'b0;
        r[13] = 32'b0;
        r[14] = 32'b0;
        r[15] = 32'b0;
        r[16] = 32'b0;
        r[17] = 32'b0;
        r[18] = 32'b0;
        r[19] = 32'b0;
        r[20] = 32'b0;
        r[21] = 32'b0;
        r[22] = 32'b0;
        r[23] = 32'b0;
        r[24] = 32'b0;
        r[25] = 32'b0;
        r[26] = 32'b0;
        r[27] = 32'b0;
        r[28] = 32'b0;
        r[29] = 32'b0;
        r[30] <= 32'b0;
        r[31] = 32'b0;
      end

    // register write (except r0)
    always @ (posedge clk)
      begin
        if (write & rw!=0)
          r[rw] = rwd;
      end


    // register read  (except r0)
    assign rd1 = rs1==0 ? 32'b0 : r[rs1];
    assign rd2 = rs2==0 ? 32'b0 : r[rs2];

endmodule

core/DATAPATH/datapath.v
/*
----------------------------------------------------------------
                         RISC-V Core
                   [ PROCESSOR DATAPATH ]
----------------------------------------------------------------

This part of the processor contains the hardware connections
necessary to perform operations required by the processor.

*/

`include "./../ALU/alu.v"
`include "./../REGISTERS/register_file.v"

module datapath(
    input [4:0]rs1, // Source register 1 offset
    input [4:0]rs2, // Source register 2 offset
    input [4:0]rw,  // write register offset
    input [6:0]operation,
    input write,
    input clk,
    input reset,
    output zero_flag
);

    // interconnections wires between 'REGISTER FILE' and 'ALU'
    wire [31:0]rd1;  // source register 2 data
    wire [31:0]rd2;  // source register 2 data
    wire [31:0]rwd;  // Write register data

    // Creating register file instance
    reg_file register_inst(
        .clk(clk),
        .reset(reset),
        .rs1(rs1),
        .rs2(rs2),
        .rd1(rd1),
        .rd2(rd2),
        .rw(rw),
        .rwd(rwd),
        .write(write)
    );

    // Creating ALU instance
    alu alu_inst(
        .ip1(rd1),
        .ip2(rd2),
        .operation(operation),
        .result(rwd),
        .zero_flag(zero_flag)
    );

endmodule

core/DATAPATH/test_datapath.v
// Testbench for Datapath module
`include "datapath.v"
`include "./../constants.v"

module testbench();

    reg [4:0] rs1;
    reg [4:0] rs2;
    reg [4:0]rw;
    reg [6:0]operation;
    reg write;
    reg clk;
    reg reset;
    wire zero_flag;


    // creating datapath instance
    datapath datapath_inst(

        .rs1(rs1),
        .rs2(rs2),
        .rw(rw),
        .operation(operation),
        .write(write),
        .clk(clk),
        .reset(reset),
        .zero_flag(zero_flag)
    );


    initial
      begin
        $dumpfile("output.vcd");
        $dumpvars(0, testbench);
      end


    initial
      begin
        clk = 0;
        forever #10 clk = ~clk;
      end


    initial
      begin
        reset = 1;
        #20 reset = 0;
      end

      initial
      begin
        write = 0;
        #10 write=1;
      end


      initial
        begin
          #25 rs1 = 5'd5; rs2 = 5'd27; operation = `ADD;
          #25 rs1 = 5'd14; rs2 = 5'd23; operation = `SUB;
          #25 rs1 = 5'd10; rs2 = 5'd14;  operation = `AND;
          #25 rs1 = 5'd7; rs2 = 5'd9; operation = `OR;
          #25 rs1 = 5'd2; rs2 = 5'd21; operation = `DIV;
        end

      initial
        #200 $finish();

endmodule

core/DATAPATH/output.vcd
$date
	Thu Feb 24 22:17:41 2022
$end
$version
	Icarus Verilog
$end
$timescale
	1s
$end
$scope module testbench $end
$var wire 1 ! zero_flag $end
$var reg 1 " clk $end
$var reg 7 # operation [6:0] $end
$var reg 1 $ reset $end
$var reg 5 % rs1 [4:0] $end
$var reg 5 & rs2 [4:0] $end
$var reg 5 ' rw [4:0] $end
$var reg 1 ( write $end
$scope module datapath_inst $end
$var wire 1 " clk $end
$var wire 7 ) operation [6:0] $end
$var wire 1 $ reset $end
$var wire 5 * rs1 [4:0] $end
$var wire 5 + rs2 [4:0] $end
$var wire 5 , rw [4:0] $end
$var wire 1 ( write $end
$var wire 1 ! zero_flag $end
$var wire 32 - rwd [31:0] $end
$var wire 32 . rd2 [31:0] $end
$var wire 32 / rd1 [31:0] $end
$scope module alu_inst $end
$var wire 7 0 operation [6:0] $end
$var wire 32 1 ip2 [31:0] $end
$var wire 32 2 ip1 [31:0] $end
$var reg 32 3 result [31:0] $end
$var reg 1 ! zero_flag $end
$upscope $end
$scope module register_inst $end
$var wire 1 " clk $end
$var wire 1 $ reset $end
$var wire 5 4 rs1 [4:0] $end
$var wire 5 5 rs2 [4:0] $end
$var wire 5 6 rw [4:0] $end
$var wire 32 7 rwd [31:0] $end
$var wire 1 ( write $end
$var wire 32 8 rd2 [31:0] $end
$var wire 32 9 rd1 [31:0] $end
$upscope $end
$upscope $end
$upscope $end
$enddefinitions $end
#0
$dumpvars
bx 9
bx 8
bx 7
bx 6
bx 5
bx 4
bx 3
bx 2
bx 1
bx 0
bx /
bx .
bx -
bx ,
bx +
bx *
bx )
0(
bx '
bx &
bx %
1$
bx #
0"
x!
$end
#10
1(
1"
#20
0"
0$
#25
1!
b0 -
b0 3
b0 7
b0 .
b0 1
b0 8
b0 /
b0 2
b0 9
b0 #
b0 )
b0 0
b11011 &
b11011 +
b11011 5
b101 %
b101 *
b101 4
#30
1"
#40
0"
#50
1"
b1 #
b1 )
b1 0
b10111 &
b10111 +
b10111 5
b1110 %
b1110 *
b1110 4
#60
0"
#70
1"
#75
b10 #
b10 )
b10 0
b1110 &
b1110 +
b1110 5
b1010 %
b1010 *
b1010 4
#80
0"
#90
1"
#100
0"
b11 #
b11 )
b11 0
b1001 &
b1001 +
b1001 5
b111 %
b111 *
b111 4
#110
1"
#120
0"
#125
0!
bx -
bx 3
bx 7
b110 #
b110 )
b110 0
b10101 &
b10101 +
b10101 5
b10 %
b10 *
b10 4
