core/DECODE/decode.v
/*
----------------------------------------------------------------
                         RISC-V Core
                   [ INSTRUCTION DECODER ]
----------------------------------------------------------------

- In this implementation of instruction decoder which takes an 32-bit
  instruction as input.
- It decodes 32 bit instruction into opcode, source registers and destination register

      -------------------------------------------------
      | opcode |   rd   | func3 |  rs1  |  rs2  | func7 |
      -------------------------------------------------
      0       6|7     11|12   14|15   19|20   24|25   31|

 - Here func3 indicated type of instruction (R-Type, Load/Store. Immediate, etc.)
 - Func7 is  used in immediate instructions.

*/

module decode(
    input [31:0] instruction,
    output reg [4:0] rs1,
    output reg [4:0] rs2,
    output reg [6:0] operation,
    output reg write,
    output reg [4:0] rw
);

    reg type; // temp
    always @(instruction)
      begin
        operation = instruction[6:0]; // opcode
        rs1 = instruction[24:20]; // source register 1
        rs2 = instruction[19:15]; // source register 2
        rw = instruction[11:7];   // destination register
        type = instruction[14:12]; // Type of Instruction

        write = (type == 3'b000) ? 1'b1 : 1'b0; // R-Type Instruction
      end

endmodule

core/DECODE/test_decode.v
// Testbench for Instruction decoder
`include "decode.v"
module testbench();

  reg [31:0] instruction;
  wire [4:0] rs1;
  wire [4:0] rs2;
  wire [6:0] operation;
  wire write;
  wire [4:0] rw;

  decode decode_inst(

      .instruction(instruction),
      .rs1(rs1),
      .rs2(rs2),
      .operation(operation),
      .write(write),
      .rw(rw)
  );

  initial
    begin
      $monitor($time, " instruction=%b, rs1=%d, rs2=%d, operation=%d, write=%b, rd=%d", instruction, rs1, rs2, operation, write, rw);
      $dumpfile("output.vcd");
      $dumpvars(0, testbench);
    end

  initial
    begin
      instruction = 32'h4A41E108;
      #10 instruction = 32'h4A41E100;
      #10 instruction = 32'h9A51B501;
      #10 instruction = 32'h78D94E0A;
      #10 instruction = 32'h13E04A0C;
      #10 instruction = 32'h4A0D1307;
      #10 instruction = 32'h104A3E06;
      #10 instruction = 32'hE01A0302;
    end

endmodule

core/DECODE/output.vcd
$date
	Sat Feb 26 23:03:45 2022
$end
$version
	Icarus Verilog
$end
$timescale
	1s
$end
$scope module testbench $end
$var wire 1 ! write $end
$var wire 5 " rw [4:0] $end
$var wire 5 # rs2 [4:0] $end
$var wire 5 $ rs1 [4:0] $end
$var wire 7 % operation [6:0] $end
$var reg 32 & instruction [31:0] $end
$scope module decode_inst $end
$var wire 32 ' instruction [31:0] $end
$var reg 7 ( operation [6:0] $end
$var reg 5 ) rs1 [4:0] $end
$var reg 5 * rs2 [4:0] $end
$var reg 5 + rw [4:0] $end
$var reg 1 , type $end
$var reg 1 ! write $end
$upscope $end
$upscope $end
$enddefinitions $end
#0
$dumpvars
0,
b10 +
b11 *
b100 )
b1000 (
b1001010010000011110000100001000 '
b1001010010000011110000100001000 &
b1000 %
b100 $
b11 #
b10 "
1!
$end
#10
b0 %
b0 (
b1001010010000011110000100000000 &
b1001010010000011110000100000000 '
#20
0!
1,
b1010 "
b1010 +
b101 $
b101 )
b1 %
b1 (
b10011010010100011011010100000001 &
b10011010010100011011010100000001 '
#30
1!
0,
b11100 "
b11100 +
b10010 #
b10010 *
b1101 $
b1101 )
b1010 %
b1010 (
b1111000110110010100111000001010 &
b1111000110110010100111000001010 '
#40
b10100 "
b10100 +
b0 #
b0 *
b11110 $
b11110 )
b1100 %
b1100 (
b10011111000000100101000001100 &
b10011111000000100101000001100 '
#50
0!
1,
b110 "
b110 +
b11010 #
b11010 *
b0 $
b0 )
b111 %
b111 (
b1001010000011010001001100000111 &
b1001010000011010001001100000111 '
#60
b11100 "
b11100 +
b10100 #
b10100 *
b100 $
b100 )
b110 %
b110 (
b10000010010100011111000000110 &
b10000010010100011111000000110 '
#70
1!
0,
b110 "
b110 +
b1 $
b1 )
b10 %
b10 (
b11100000000110100000001100000010 &
b11100000000110100000001100000010 '
